batchbald_redux/__init__.py
batchbald_redux/_nbdev.py
batchbald_redux/active_learning.py
batchbald_redux/batchbald.py
batchbald_redux/consistent_mc_dropout.py
batchbald_redux/joint_entropy.py
batchbald_redux/repeated_mnist.py
batchbald_redux-2.0.5.dist-info/LICENSE
batchbald_redux-2.0.5.dist-info/METADATA
batchbald_redux-2.0.5.dist-info/WHEEL
batchbald_redux-2.0.5.dist-info/entry_points.txt
batchbald_redux-2.0.5.dist-info/top_level.txt
batchbald_redux-2.0.5.dist-info/RECORD
