Metadata-Version: 2.1
Name: batchbald-redux
Version: 2.0.5
Summary: An implementation of the BatchBALD algorithm
Home-page: https://github.com/blackhc/batchbald_redux/tree/master/
Author: Andreas Kirsch
Author-email: blackhc+batchbald@gmail.com
License: Apache Software License 2.0
Keywords: Active Learning,Machine Learning,PyTorch
Platform: UNKNOWN
Classifier: Development Status :: 3 - Alpha
Classifier: Intended Audience :: Developers
Classifier: License :: OSI Approved :: Apache Software License
Classifier: Natural Language :: English
Classifier: Programming Language :: Python :: 3.7
Classifier: Programming Language :: Python :: 3.8
Requires-Python: >=3.7
Requires-Dist: torch
Requires-Dist: torchvision
Requires-Dist: numpy
Requires-Dist: tqdm
Requires-Dist: blackhc.project (~=2.1)
Requires-Dist: toma (<2)
